pptestmichalkowalewski/__init__.py
pptestmichalkowalewski/m_mod_pptest.py
pptestmichalkowalewski-0.0.1.dist-info/LICENSE.txt
pptestmichalkowalewski-0.0.1.dist-info/METADATA
pptestmichalkowalewski-0.0.1.dist-info/WHEEL
pptestmichalkowalewski-0.0.1.dist-info/top_level.txt
pptestmichalkowalewski-0.0.1.dist-info/RECORD
